gitlab_activity/__init__.py
gitlab_activity/_version.py
gitlab_activity/cache.py
gitlab_activity/cli.py
gitlab_activity/git.py
gitlab_activity/graphql.py
gitlab_activity/lib.py
gitlab_activity/schema.json
gitlab_activity/utils.py
gitlab_activity-0.2.0.dist-info/METADATA
gitlab_activity-0.2.0.dist-info/WHEEL
gitlab_activity-0.2.0.dist-info/entry_points.txt
gitlab_activity-0.2.0.dist-info/licenses/LICENSE
gitlab_activity-0.2.0.dist-info/RECORD
