Metadata-Version: 2.4
Name: gitlab_activity
Version: 0.2.0
Summary: Grab recent issue/PR activity from a GitLab repository and render it as markdown.
Project-URL: Homepage, https://mahendrapaipuri.gitlab.io/gitlab-activity/
Project-URL: Source Code, https://gitlab.com/mahendrapaipuri/gitlab-activity
Author-email: Mahendra Paipuri <mahendra.paipuri@gmail.com>
License: BSD 3-Clause License
License-File: LICENSE
Classifier: Intended Audience :: Developers
Classifier: Intended Audience :: Science/Research
Classifier: License :: OSI Approved :: BSD License
Classifier: Operating System :: OS Independent
Classifier: Programming Language :: Python
Classifier: Programming Language :: Python :: 3
Classifier: Programming Language :: Python :: 3.9
Classifier: Programming Language :: Python :: 3.10
Classifier: Programming Language :: Python :: 3.11
Classifier: Programming Language :: Python :: 3.12
Classifier: Programming Language :: Python :: 3.13
Classifier: Topic :: Software Development :: Build Tools
Classifier: Topic :: Software Development :: Version Control :: Git
Requires-Python: >=3.9
Requires-Dist: click
Requires-Dist: importlib-resources
Requires-Dist: jsonschema
Requires-Dist: markdown
Requires-Dist: numpy
Requires-Dist: pandas
Requires-Dist: python-dateutil; python_version < '3.12'
Requires-Dist: requests
Requires-Dist: toml
Requires-Dist: tqdm
Provides-Extra: dev
Requires-Dist: pre-commit; extra == 'dev'
Requires-Dist: pytest; extra == 'dev'
Requires-Dist: pytest-cov>=2.6.1; extra == 'dev'
Requires-Dist: pytest-regressions; extra == 'dev'
Provides-Extra: test
Requires-Dist: pytest; extra == 'test'
Requires-Dist: pytest-regressions; extra == 'test'
Provides-Extra: test-cov
Requires-Dist: pytest; extra == 'test-cov'
Requires-Dist: pytest-cov>=2.6.1; extra == 'test-cov'
Requires-Dist: pytest-regressions; extra == 'test-cov'
